redis_cooker/__init__.py
redis_cooker/abn_test.py
redis_cooker/adapters.py
redis_cooker/atomic.py
redis_cooker/clients.py
redis_cooker/collections.py
redis_cooker/mixins.py
redis_cooker/utils.py
tests/__init__.py
tests/test_abn_test.py
tests/test_adapters.py
tests/test_collections.py
redis_cooker-2020.12.1.dist-info/LICENSE
redis_cooker-2020.12.1.dist-info/METADATA
redis_cooker-2020.12.1.dist-info/WHEEL
redis_cooker-2020.12.1.dist-info/top_level.txt
redis_cooker-2020.12.1.dist-info/RECORD
