Metadata-Version: 2.1
Name: redis-cooker
Version: 2020.12.1
Summary: An redis python datastructures package.
Home-page: https://github.com/Ed-XCF/redis-cooker
Author: Ed__xu__Ed
Author-email: m.tofu@qq.com
License: UNKNOWN
Platform: UNKNOWN
Classifier: Programming Language :: Python :: 3
Classifier: License :: OSI Approved :: MIT License
Classifier: Operating System :: OS Independent
Requires-Python: >=3.6
Requires-Dist: redis (>=3.5.3)
Requires-Dist: attrs (>=20.3.0)
